pytest_android/__init__.py
pytest_android/__main__.py
pytest_android/fixtrues.py
pytest_android/hooks.py
pytest_android/utils.py
pytest_android-2019.2a3.dist-info/LICENSE
pytest_android-2019.2a3.dist-info/METADATA
pytest_android-2019.2a3.dist-info/WHEEL
pytest_android-2019.2a3.dist-info/entry_points.txt
pytest_android-2019.2a3.dist-info/top_level.txt
pytest_android-2019.2a3.dist-info/RECORD
