Metadata-Version: 2.1
Name: pytest-android
Version: 2019.2a3
Summary: This fixture provides a configured "driver" for Android Automated Testing, using uiautomator2.
Home-page: https://github.com/edsion1107/pytest-android
Author: edsion
Author-email: edsion@i1hao.com
Maintainer: edsion
Maintainer-email: edsion@i1hao.com
License: MIT
Platform: UNKNOWN
Classifier: Development Status :: 3 - Alpha
Classifier: Framework :: Pytest
Classifier: Intended Audience :: Developers
Classifier: Topic :: Software Development :: Testing
Classifier: Topic :: Software Development :: Quality Assurance
Classifier: Programming Language :: Python
Classifier: Programming Language :: Python :: 3 :: Only
Classifier: Programming Language :: Python :: 3.6
Classifier: Programming Language :: Python :: 3.7
Classifier: Programming Language :: Python :: Implementation :: CPython
Classifier: Operating System :: MacOS
Classifier: Operating System :: Android
Classifier: Operating System :: POSIX :: Linux
Classifier: Operating System :: Microsoft :: Windows
Classifier: Natural Language :: Chinese (Simplified)
Classifier: License :: OSI Approved :: MIT License
Requires-Python: ~=3.6
Requires-Dist: pytest
Requires-Dist: pytest-variables
Requires-Dist: progressbar2
Requires-Dist: requests-download
Requires-Dist: retry
Requires-Dist: uiautomator2
Provides-Extra: allure
Requires-Dist: pillow ; extra == 'allure'
Requires-Dist: allure-pytest ; extra == 'allure'
Provides-Extra: hjson
Requires-Dist: hjson ; extra == 'hjson'
Provides-Extra: rerunfailures
Requires-Dist: pytest-rerunfailures ; extra == 'rerunfailures'
Provides-Extra: weditor
Requires-Dist: weditor ; extra == 'weditor'
Provides-Extra: yaml
Requires-Dist: PyYAML ; extra == 'yaml'
